{
  "type": "FeatureCollection",
  "features": [
    {
      "type": "Feature",
      "properties": {
        "type": "QR",
        "rows": 21,
        "cols": 21,
        "polarity": 1,
        "x": 1302.5,
        "y": -977.5,
        "w": 430.9812662656862,
        "h": 425.0001742682298,
        "theta": 1.5614725876577258
      },
      "geometry": {
        "type": "Polygon",
        "coordinates": [
          [
            [
              1512.9817013207867,
              -1194.9625333456484
            ],
            [
              1517.0000000000002,
              -764.0000000000001
            ],
            [
              1092.0182986792136,
              -760.0374666543518
            ],
            [
              1088.0,
              -1191.0
            ],
            [
              1512.9817013207867,
              -1194.9625333456484
            ]
          ]
        ]
      }
    }
  ]
}