{
  "type": "FeatureCollection",
  "features": [
    {
      "type": "Feature",
      "properties": {
        "type": "Datamatrix",
        "rows": 16,
        "cols": 16,
        "polarity": 0,
        "x": 1365.5,
        "y": -1027.0,
        "w": 235.81555272983485,
        "h": 233.42670175179688,
        "theta": -2.1053421794880265
      },
      "geometry": {
        "type": "Polygon",
        "coordinates": [
          [
            [
              1325.136303654558,
              -866.0806971885195
            ],
            [
              1205.0,
              -1069.0
            ],
            [
              1405.8636963454417,
              -1187.9193028114803
            ],
            [
              1525.9999999999998,
              -984.9999999999998
            ],
            [
              1325.136303654558,
              -866.0806971885195
            ]
          ]
        ]
      }
    }
  ]
}