{
  "type": "FeatureCollection",
  "features": [
    {
      "type": "Feature",
      "properties": {
        "type": "Datamatrix",
        "rows": 10,
        "cols": 10,
        "polarity": 1,
        "x": 1292.0000000000002,
        "y": -966.0,
        "w": 207.98034620357072,
        "h": 201.98063172750705,
        "theta": 0.009755788045514873
      },
      "geometry": {
        "type": "Polygon",
        "coordinates": [
          [
            [
              1189.0000000000002,
              -1068.0
            ],
            [
              1396.9704489757075,
              -1065.971020009993
            ],
            [
              1395.0000000000002,
              -864.0000000000001
            ],
            [
              1187.029551024293,
              -866.028979990007
            ],
            [
              1189.0000000000002,
              -1068.0
            ]
          ]
        ]
      }
    }
  ]
}