{
  "type": "FeatureCollection",
  "features": [
    {
      "type": "Feature",
      "properties": {
        "type": "Datamatrix",
        "rows": 18,
        "cols": 18,
        "polarity": 0,
        "x": 1274.0000000000002,
        "y": -1106.5,
        "w": 671.6537766391699,
        "h": 636.9161674242068,
        "theta": -1.5904609625980641
      },
      "geometry": {
        "type": "Polygon",
        "coordinates": [
          [
            [
              962.206975680066,
              -764.4760827289574
            ],
            [
              949.0000000000001,
              -1436.0
            ],
            [
              1585.7930243199344,
              -1448.5239172710426
            ],
            [
              1599.0000000000002,
              -777.0
            ],
            [
              962.206975680066,
              -764.4760827289574
            ]
          ]
        ]
      }
    }
  ]
}