{
  "type": "FeatureCollection",
  "features": [
    {
      "type": "Feature",
      "properties": {
        "type": "Datamatrix",
        "rows": 16,
        "cols": 16,
        "polarity": 1,
        "x": 656.0843369734789,
        "y": -1067.9678939157566,
        "w": 537.0754136990447,
        "h": 527.0097881609721,
        "theta": -0.01675820758223748
      },
      "geometry": {
        "type": "Polygon",
        "coordinates": [
          [
            [
              383.1686739469579,
              -1326.9357878315132
            ],
            [
              920.1686739469579,
              -1335.9357878315132
            ],
            [
              929.0,
              -808.9999999999999
            ],
            [
              392.0,
              -799.9999999999999
            ],
            [
              383.1686739469579,
              -1326.9357878315132
            ]
          ]
        ]
      }
    }
  ]
}