{
  "type": "FeatureCollection",
  "features": [
    {
      "type": "Feature",
      "properties": {
        "type": "Datamatrix",
        "rows": 16,
        "cols": 16,
        "polarity": 1,
        "x": 1698.8489450552884,
        "y": -953.1451663356113,
        "w": 255.52319866607013,
        "h": 263.86385932736226,
        "theta": 1.7456976208735846
      },
      "geometry": {
        "type": "Polygon",
        "coordinates": [
          [
            [
              1850.9999999999995,
              -1055.9999999999995
            ],
            [
              1806.5361684157838,
              -804.3751348984154
            ],
            [
              1546.6978901105772,
              -850.290332671223
            ],
            [
              1591.161721694793,
              -1101.9151977728072
            ],
            [
              1850.9999999999995,
              -1055.9999999999995
            ]
          ]
        ]
      }
    }
  ]
}