{
  "type": "FeatureCollection",
  "features": [
    {
      "type": "Feature",
      "properties": {
        "type": "Datamatrix",
        "rows": 40,
        "cols": 40,
        "polarity": 1,
        "x": 1292.4975414995183,
        "y": -968.4963023910093,
        "w": 812.0006157633134,
        "h": 808.0080079535861,
        "theta": 3.140361127118799
      },
      "geometry": {
        "type": "Polygon",
        "coordinates": [
          [
            [
              1698.9950829990369,
              -564.9926047820185
            ],
            [
              886.9950829990369,
              -563.9926047820185
            ],
            [
              885.9999999999999,
              -1372.0
            ],
            [
              1698.0,
              -1373.0
            ],
            [
              1698.9950829990369,
              -564.9926047820185
            ]
          ]
        ]
      }
    }
  ]
}