{
  "type": "FeatureCollection",
  "features": [
    {
      "type": "Feature",
      "properties": {
        "type": "Datamatrix",
        "rows": 18,
        "cols": 18,
        "polarity": 1,
        "x": 1217.9999999999995,
        "y": -688.4999999999998,
        "w": 281.21521733186995,
        "h": 280.1767326902592,
        "theta": 3.1023271313719842
      },
      "geometry": {
        "type": "Polygon",
        "coordinates": [
          [
            [
              1363.9984590109648,
              -554.0392251754306
            ],
            [
              1082.9999999999998,
              -542.9999999999999
            ],
            [
              1072.0015409890345,
              -822.960774824569
            ],
            [
              1352.9999999999995,
              -833.9999999999997
            ],
            [
              1363.9984590109648,
              -554.0392251754306
            ]
          ]
        ]
      }
    }
  ]
}