{
  "type": "FeatureCollection",
  "features": [
    {
      "type": "Feature",
      "properties": {
        "type": "QR",
        "rows": 25,
        "cols": 25,
        "polarity": 1,
        "x": 1300.5299253423432,
        "y": -974.670381384631,
        "w": 506.8589547398764,
        "h": 505.71070630792605,
        "theta": 0.9592622164688043
      },
      "geometry": {
        "type": "Polygon",
        "coordinates": [
          [
            [
              1362.0598506846864,
              -1327.340762769262
            ],
            [
              1653.0598506846864,
              -912.3407627692619
            ],
            [
              1239.0000000000002,
              -622.0
            ],
            [
              948.0000000000002,
              -1037.0
            ],
            [
              1362.0598506846864,
              -1327.340762769262
            ]
          ]
        ]
      }
    }
  ]
}