{
  "type": "FeatureCollection",
  "features": [
    {
      "type": "Feature",
      "properties": {
        "type": "Datamatrix",
        "rows": 10,
        "cols": 10,
        "polarity": 1,
        "x": 1284.2577251896123,
        "y": -969.3448798006057,
        "w": 193.1657319505714,
        "h": 204.86552972100756,
        "theta": -0.04142706186054587
      },
      "geometry": {
        "type": "Polygon",
        "coordinates": [
          [
            [
              1183.5154503792244,
              -1067.6897596012113
            ],
            [
              1376.5154503792244,
              -1075.6897596012113
            ],
            [
              1385.0,
              -871.0000000000001
            ],
            [
              1192.0,
              -863.0
            ],
            [
              1183.5154503792244,
              -1067.6897596012113
            ]
          ]
        ]
      }
    }
  ]
}