{
  "type": "FeatureCollection",
  "features": [
    {
      "type": "Feature",
      "properties": {
        "type": "QR",
        "rows": 21,
        "cols": 21,
        "polarity": 1,
        "x": 1292.5,
        "y": -563.0,
        "w": 253.96729486552763,
        "h": 247.0660096789644,
        "theta": -1.6025317003233546
      },
      "geometry": {
        "type": "Polygon",
        "coordinates": [
          [
            [
              1173.058394160584,
              -432.16058394160586
            ],
            [
              1165.0,
              -686.0
            ],
            [
              1411.941605839416,
              -693.8394160583941
            ],
            [
              1420.0,
              -440.0
            ],
            [
              1173.058394160584,
              -432.16058394160586
            ]
          ]
        ]
      }
    }
  ]
}