{
  "type": "FeatureCollection",
  "features": [
    {
      "type": "Feature",
      "properties": {
        "type": "Datamatrix",
        "rows": 40,
        "cols": 40,
        "polarity": 1,
        "x": 1291.996381395857,
        "y": -972.4890556048501,
        "w": 823.0024301300696,
        "h": 813.9951663254795,
        "theta": 1.5683661979212868
      },
      "geometry": {
        "type": "Polygon",
        "coordinates": [
          [
            [
              1697.9927627917139,
              -1384.9781112097003
            ],
            [
              1699.9927627917139,
              -561.9781112097003
            ],
            [
              886.0000000000001,
              -559.9999999999999
            ],
            [
              884.0000000000001,
              -1382.9999999999998
            ],
            [
              1697.9927627917139,
              -1384.9781112097003
            ]
          ]
        ]
      }
    }
  ]
}