{
  "type": "FeatureCollection",
  "features": [
    {
      "type": "Feature",
      "properties": {
        "type": "Datamatrix",
        "rows": 40,
        "cols": 40,
        "polarity": 1,
        "x": 1291.9993834781258,
        "y": -967.4999992398004,
        "w": 811.0030826119475,
        "h": 812.0006157623768,
        "theta": -0.0012330449977802558
      },
      "geometry": {
        "type": "Polygon",
        "coordinates": [
          [
            [
              885.997533912504,
              -1372.9999969592016
            ],
            [
              1696.9999999999998,
              -1373.9999999999998
            ],
            [
              1698.0012330437478,
              -562.0000015203992
            ],
            [
              886.9987669562519,
              -560.9999984796008
            ],
            [
              885.997533912504,
              -1372.9999969592016
            ]
          ]
        ]
      }
    }
  ]
}