{
  "type": "FeatureCollection",
  "features": [
    {
      "type": "Feature",
      "properties": {
        "type": "Datamatrix",
        "rows": 16,
        "cols": 16,
        "polarity": 1,
        "x": 1542.5,
        "y": -798.0,
        "w": 103.20879775164397,
        "h": 99.36268950999826,
        "theta": -2.7919855297993905
      },
      "geometry": {
        "type": "Polygon",
        "coordinates": [
          [
            [
              1573.9654247677427,
              -733.6480222200937
            ],
            [
              1477.0,
              -769.0
            ],
            [
              1511.0345752322576,
              -862.3519777799063
            ],
            [
              1608.0000000000002,
              -827.0
            ],
            [
              1573.9654247677427,
              -733.6480222200937
            ]
          ]
        ]
      }
    }
  ]
}