{
  "type": "FeatureCollection",
  "features": [
    {
      "type": "Feature",
      "properties": {
        "type": "QR",
        "rows": 21,
        "cols": 21,
        "polarity": 0,
        "x": 1321.0,
        "y": -966.0000000000002,
        "w": 183.00822656011718,
        "h": 181.00825674902453,
        "theta": 3.136098203386577
      },
      "geometry": {
        "type": "Polygon",
        "coordinates": [
          [
            [
              1413.0,
              -876.0000000000001
            ],
            [
              1229.9945358490568,
              -874.9944754716983
            ],
            [
              1229.0000000000002,
              -1056.0000000000002
            ],
            [
              1412.0054641509435,
              -1057.005524528302
            ],
            [
              1413.0,
              -876.0000000000001
            ]
          ]
        ]
      }
    }
  ]
}