{
  "type": "FeatureCollection",
  "features": [
    {
      "type": "Feature",
      "properties": {
        "type": "Datamatrix",
        "rows": 8,
        "cols": 32,
        "polarity": 0,
        "x": 1457.0889728056964,
        "y": -872.2064919310922,
        "w": 1153.839243569051,
        "h": 283.79343294576023,
        "theta": -3.10344984372084
      },
      "geometry": {
        "type": "Polygon",
        "coordinates": [
          [
            [
              2028.1779456113927,
              -708.4129838621843
            ],
            [
              875.1779456113929,
              -752.4129838621843
            ],
            [
              885.9999999999999,
              -1036.0
            ],
            [
              2038.9999999999998,
              -992.0
            ],
            [
              2028.1779456113927,
              -708.4129838621843
            ]
          ]
        ]
      }
    }
  ]
}