{
  "type": "FeatureCollection",
  "features": [
    {
      "type": "Feature",
      "properties": {
        "type": "Datamatrix",
        "rows": 16,
        "cols": 36,
        "polarity": 1,
        "x": 1298.5000000000002,
        "y": -963.0000000000001,
        "w": 731.8838008055097,
        "h": 324.8247252265153,
        "theta": 2.5304179065537253
      },
      "geometry": {
        "type": "Polygon",
        "coordinates": [
          [
            [
              1691.394153779787,
              -1039.9768401901852
            ],
            [
              1092.0000000000002,
              -620.0000000000001
            ],
            [
              905.6058462202134,
              -886.0231598098151
            ],
            [
              1505.0000000000005,
              -1306.0000000000002
            ],
            [
              1691.394153779787,
              -1039.9768401901852
            ]
          ]
        ]
      }
    }
  ]
}