{
  "type": "FeatureCollection",
  "features": [
    {
      "type": "Feature",
      "properties": {
        "type": "Datamatrix",
        "rows": 16,
        "cols": 16,
        "polarity": 1,
        "x": 1425.9999999999998,
        "y": -1031.5,
        "w": 264.76252743735773,
        "h": 255.33077383069678,
        "theta": 1.5215936460244988
      },
      "geometry": {
        "type": "Polygon",
        "coordinates": [
          [
            [
              1546.9999999999998,
              -1170.0
            ],
            [
              1560.0217705575035,
              -905.5578902168467
            ],
            [
              1304.9999999999998,
              -892.9999999999999
            ],
            [
              1291.978229442496,
              -1157.4421097831532
            ],
            [
              1546.9999999999998,
              -1170.0
            ]
          ]
        ]
      }
    }
  ]
}