{
  "type": "FeatureCollection",
  "features": [
    {
      "type": "Feature",
      "properties": {
        "type": "QR",
        "rows": 21,
        "cols": 21,
        "polarity": 0,
        "x": 1623.0000000000005,
        "y": -532.5,
        "w": 792.6097338163328,
        "h": 561.5361162557601,
        "theta": 2.7252283876831025
      },
      "geometry": {
        "type": "Polygon",
        "coordinates": [
          [
            [
              2099.0000000000005,
              -436.0
            ],
            [
              1374.1065532100802,
              -115.43849117302454
            ],
            [
              1147.0000000000002,
              -629.0000000000001
            ],
            [
              1871.8934467899203,
              -949.5615088269756
            ],
            [
              2099.0000000000005,
              -436.0
            ]
          ]
        ]
      }
    }
  ]
}