{
  "type": "FeatureCollection",
  "features": [
    {
      "type": "Feature",
      "properties": {
        "type": "QR",
        "rows": 41,
        "cols": 41,
        "polarity": 1,
        "x": 1298.0000000000002,
        "y": -970.5,
        "w": 939.5624212590712,
        "h": 852.2907112938592,
        "theta": -2.0329101946670534
      },
      "geometry": {
        "type": "Polygon",
        "coordinates": [
          [
            [
              1126.0,
              -360.0
            ],
            [
              707.1043154044295,
              -1201.01364368803
            ],
            [
              1470.0000000000005,
              -1581.0
            ],
            [
              1888.8956845955709,
              -739.9863563119701
            ],
            [
              1126.0,
              -360.0
            ]
          ]
        ]
      }
    }
  ]
}