{
  "type": "FeatureCollection",
  "features": [
    {
      "type": "Feature",
      "properties": {
        "type": "Datamatrix",
        "rows": 18,
        "cols": 18,
        "polarity": 0
      },
      "geometry": {
        "type": "Polygon",
        "coordinates": [
          [
            [
              1560.0,
              -1106.0
            ],
            [
              1132.0,
              -1110.0
            ],
            [
              1127.0,
              -677.0
            ],
            [
              1559.0,
              -681.0
            ],
            [
              1560.0,
              -1106.0
            ]
          ]
        ]
      }
    }
  ]
}