{
  "type": "FeatureCollection",
  "features": [
    {
      "type": "Feature",
      "properties": {
        "type": "Datamatrix",
        "rows": 10,
        "cols": 10,
        "polarity": 1,
        "x": 1291.4975001237563,
        "y": -966.9975248750063,
        "w": 201.00248754679617,
        "h": 201.9975001082873,
        "theta": 1.5757714101257507
      },
      "geometry": {
        "type": "Polygon",
        "coordinates": [
          [
            [
              1392.9950002475125,
              -1066.9950497500124
            ],
            [
              1391.9950002475125,
              -865.9950497500125
            ],
            [
              1190.0,
              -867.0000000000001
            ],
            [
              1191.0,
              -1068.0
            ],
            [
              1392.9950002475125,
              -1066.9950497500124
            ]
          ]
        ]
      }
    }
  ]
}