{
  "type": "FeatureCollection",
  "features": [
    {
      "type": "Feature",
      "properties": {
        "type": "QR",
        "rows": 45,
        "cols": 45,
        "polarity": 1,
        "x": 1301.4999999999998,
        "y": -977.0,
        "w": 936.9804890758427,
        "h": 913.9740494626718,
        "theta": -3.1394281548055627
      },
      "geometry": {
        "type": "Polygon",
        "coordinates": [
          [
            [
              1768.9999999999998,
              -518.9999999999999
            ],
            [
              832.0217058258567,
              -521.0280915458314
            ],
            [
              833.9999999999999,
              -1435.0
            ],
            [
              1770.978294174143,
              -1432.9719084541684
            ],
            [
              1768.9999999999998,
              -518.9999999999999
            ]
          ]
        ]
      }
    }
  ]
}