{
  "type": "FeatureCollection",
  "features": [
    {
      "type": "Feature",
      "properties": {
        "type": "Datamatrix",
        "rows": 16,
        "cols": 36,
        "polarity": 1,
        "x": 1291.0,
        "y": -967.0,
        "w": 730.4431502694615,
        "h": 322.99969694169124,
        "theta": -3.1402227914329544
      },
      "geometry": {
        "type": "Polygon",
        "coordinates": [
          [
            [
              1655.9999999999998,
              -805.0
            ],
            [
              925.5575350768718,
              -806.0006061163331
            ],
            [
              926.0000000000001,
              -1129.0
            ],
            [
              1656.442464923128,
              -1127.999393883667
            ],
            [
              1655.9999999999998,
              -805.0
            ]
          ]
        ]
      }
    }
  ]
}