{
  "type": "FeatureCollection",
  "features": [
    {
      "type": "Feature",
      "properties": {
        "type": "QR",
        "rows": 25,
        "cols": 25,
        "polarity": 1,
        "x": 1500.0196204731492,
        "y": -1053.987464963441,
        "w": 791.9608576186074,
        "h": 766.494952572941,
        "theta": -2.354408777804708
      },
      "geometry": {
        "type": "Polygon",
        "coordinates": [
          [
            [
              1508.0392409462984,
              -502.97492992688166
            ],
            [
              949.0392409462982,
              -1063.9749299268817
            ],
            [
              1492.0000000000002,
              -1605.0000000000002
            ],
            [
              2051.0000000000005,
              -1044.0000000000002
            ],
            [
              1508.0392409462984,
              -502.97492992688166
            ]
          ]
        ]
      }
    }
  ]
}