{
  "type": "FeatureCollection",
  "features": [
    {
      "type": "Feature",
      "properties": {
        "type": "Datamatrix",
        "rows": 40,
        "cols": 40,
        "polarity": 1,
        "x": 742.9701651467881,
        "y": -601.7791717662948,
        "w": 555.0036035919047,
        "h": 400.06226727721133,
        "theta": -1.5743999147998724
      },
      "geometry": {
        "type": "Polygon",
        "coordinates": [
          [
            [
              543.9403302935763,
              -323.55834353258945
            ],
            [
              541.9403302935763,
              -878.5583435325896
            ],
            [
              942.0,
              -880.0000000000001
            ],
            [
              944.0,
              -325.0
            ],
            [
              543.9403302935763,
              -323.55834353258945
            ]
          ]
        ]
      }
    }
  ]
}