{
  "type": "FeatureCollection",
  "features": [
    {
      "type": "Feature",
      "properties": {
        "type": "Datamatrix",
        "rows": 120,
        "cols": 120,
        "polarity": 1,
        "x": 1366.6180365892426,
        "y": -983.7196884301243,
        "w": 1806.099941863683,
        "h": 1783.6593232353598,
        "theta": -3.1310725544374773
      },
      "geometry": {
        "type": "Polygon",
        "coordinates": [
          [
            [
              2260.236073178485,
              -82.43937686024849
            ],
            [
              454.2360731784854,
              -101.43937686024849
            ],
            [
              473.0,
              -1885.0
            ],
            [
              2278.9999999999995,
              -1866.0
            ],
            [
              2260.236073178485,
              -82.43937686024849
            ]
          ]
        ]
      }
    }
  ]
}