{
  "type": "FeatureCollection",
  "features": [
    {
      "type": "Feature",
      "properties": {
        "type": "Datamatrix",
        "rows": 40,
        "cols": 40,
        "polarity": 1
      },
      "geometry": {
        "type": "Polygon",
        "coordinates": [
          [
            [
              593.0,
              -869.0
            ],
            [
              595.0,
              -347.0
            ],
            [
              994.0,
              -339.0
            ],
            [
              991.0,
              -890.0
            ],
            [
              593.0,
              -869.0
            ]
          ]
        ]
      }
    }
  ]
}