{
  "type": "FeatureCollection",
  "features": [
    {
      "type": "Feature",
      "properties": {
        "type": "QR",
        "rows": 21,
        "cols": 21,
        "polarity": 1,
        "x": 851.0358480411892,
        "y": -1168.416044663856,
        "w": 1086.2435270232916,
        "h": 1042.401608691677,
        "theta": 3.1204171819882136
      },
      "geometry": {
        "type": "Polygon",
        "coordinates": [
          [
            [
              1405.0716960823784,
              -658.8320893277116
            ],
            [
              319.0716960823782,
              -635.8320893277116
            ],
            [
              297.0000000000001,
              -1678.0000000000002
            ],
            [
              1383.0000000000002,
              -1701.0000000000002
            ],
            [
              1405.0716960823784,
              -658.8320893277116
            ]
          ]
        ]
      }
    }
  ]
}