{
  "type": "FeatureCollection",
  "features": [
    {
      "type": "Feature",
      "properties": {
        "type": "Datamatrix",
        "rows": 40,
        "cols": 40,
        "polarity": 1,
        "x": 1390.9750860366712,
        "y": -1579.5037404795485,
        "w": 421.0106887004177,
        "h": 414.017992127588,
        "theta": 0.007125770126432827
      },
      "geometry": {
        "type": "Polygon",
        "coordinates": [
          [
            [
              1181.9501720733426,
              -1788.0074809590972
            ],
            [
              1602.9501720733426,
              -1785.0074809590972
            ],
            [
              1600.0,
              -1371.0
            ],
            [
              1179.0,
              -1374.0
            ],
            [
              1181.9501720733426,
              -1788.0074809590972
            ]
          ]
        ]
      }
    }
  ]
}