{
  "type": "FeatureCollection",
  "features": [
    {
      "type": "Feature",
      "properties": {
        "type": "QR",
        "rows": 37,
        "cols": 37,
        "polarity": 1,
        "x": 1292.499209017204,
        "y": -613.4859600553689,
        "w": 355.5629339512205,
        "h": 391.61843573690106,
        "theta": 1.6270748630836587
      },
      "geometry": {
        "type": "Polygon",
        "coordinates": [
          [
            [
              1497.998418034408,
              -779.9719201107376
            ],
            [
              1477.998418034408,
              -424.97192011073764
            ],
            [
              1087.0,
              -447.00000000000006
            ],
            [
              1107.0,
              -802.0
            ],
            [
              1497.998418034408,
              -779.9719201107376
            ]
          ]
        ]
      }
    }
  ]
}