{
  "type": "FeatureCollection",
  "features": [
    {
      "type": "Feature",
      "properties": {
        "type": "Datamatrix",
        "rows": 18,
        "cols": 18,
        "polarity": 1,
        "x": 1494.969130808448,
        "y": -989.4593481593872,
        "w": 613.9983713333448,
        "h": 612.9153065712092,
        "theta": 0.05703432479886481
      },
      "geometry": {
        "type": "Polygon",
        "coordinates": [
          [
            [
              1205.938261616896,
              -1312.9186963187744
            ],
            [
              1818.938261616896,
              -1277.9186963187744
            ],
            [
              1784.0,
              -665.9999999999999
            ],
            [
              1171.0,
              -700.9999999999999
            ],
            [
              1205.938261616896,
              -1312.9186963187744
            ]
          ]
        ]
      }
    }
  ]
}