{
  "type": "FeatureCollection",
  "features": [
    {
      "type": "Feature",
      "properties": {
        "type": "Datamatrix",
        "rows": 40,
        "cols": 40,
        "polarity": 1,
        "x": 1489.1780182191567,
        "y": -947.6138683531427,
        "w": 1043.6920043767702,
        "h": 995.0157667636091,
        "theta": 1.5343790691053178
      },
      "geometry": {
        "type": "Polygon",
        "coordinates": [
          [
            [
              1967.3560364383136,
              -1487.2277367062854
            ],
            [
              2005.3560364383136,
              -444.22773670628555
            ],
            [
              1010.9999999999999,
              -407.99999999999994
            ],
            [
              972.9999999999999,
              -1450.9999999999998
            ],
            [
              1967.3560364383136,
              -1487.2277367062854
            ]
          ]
        ]
      }
    }
  ]
}