{
  "type": "FeatureCollection",
  "features": [
    {
      "type": "Feature",
      "properties": {
        "type": "QR",
        "rows": 37,
        "cols": 37,
        "polarity": 1,
        "x": 1414.1505912465889,
        "y": -390.8221035263259,
        "w": 486.17383722286024,
        "h": 437.51223063551265,
        "theta": -3.114850059355089
      },
      "geometry": {
        "type": "Polygon",
        "coordinates": [
          [
            [
              1651.301182493178,
              -165.6442070526516
            ],
            [
              1165.3011824931777,
              -178.6442070526516
            ],
            [
              1176.9999999999998,
              -616.0000000000002
            ],
            [
              1663.0,
              -603.0000000000002
            ],
            [
              1651.301182493178,
              -165.6442070526516
            ]
          ]
        ]
      }
    }
  ]
}