{
  "type": "FeatureCollection",
  "features": [
    {
      "type": "Feature",
      "properties": {
        "type": "Datamatrix",
        "rows": 40,
        "cols": 40,
        "polarity": 1,
        "x": 1556.3136585365855,
        "y": -654.9629268292683,
        "w": 1056.51549917642,
        "h": 958.0947944342211,
        "theta": 1.5395564933646284
      },
      "geometry": {
        "type": "Polygon",
        "coordinates": [
          [
            [
              2018.627317073171,
              -1197.9258536585367
            ],
            [
              2051.627317073171,
              -141.9258536585366
            ],
            [
              1093.9999999999998,
              -112.0
            ],
            [
              1060.9999999999998,
              -1168.0
            ],
            [
              2018.627317073171,
              -1197.9258536585367
            ]
          ]
        ]
      }
    }
  ]
}