{
  "type": "FeatureCollection",
  "features": [
    {
      "type": "Feature",
      "properties": {
        "type": "QR",
        "rows": 37,
        "cols": 37,
        "polarity": 1
      },
      "geometry": {
        "type": "Polygon",
        "coordinates": [
          [
            [
              1088.0,
              -1409.0
            ],
            [
              640.0,
              -1413.0
            ],
            [
              629.0,
              -1001.0
            ],
            [
              1087.0,
              -988.0
            ],
            [
              1088.0,
              -1409.0
            ]
          ]
        ]
      }
    }
  ]
}