{
  "type": "FeatureCollection",
  "features": [
    {
      "type": "Feature",
      "properties": {
        "type": "Datamatrix",
        "rows": 40,
        "cols": 40,
        "polarity": 1,
        "x": 1096.0,
        "y": -1112.0,
        "w": 382.9432960543299,
        "h": 366.95290161960247,
        "theta": -0.03465278946180601
      },
      "geometry": {
        "type": "Polygon",
        "coordinates": [
          [
            [
              898.286603122292,
              -1288.7326022415727
            ],
            [
              1280.9999999999998,
              -1301.9999999999998
            ],
            [
              1293.7133968777077,
              -935.2673977584271
            ],
            [
              910.9999999999999,
              -921.9999999999999
            ],
            [
              898.286603122292,
              -1288.7326022415727
            ]
          ]
        ]
      }
    }
  ]
}