{
  "type": "FeatureCollection",
  "features": [
    {
      "type": "Feature",
      "properties": {
        "type": "QR",
        "rows": 25,
        "cols": 25,
        "polarity": 1,
        "x": 1316.0,
        "y": -773.5,
        "w": 922.2068578616077,
        "h": 908.369699688965,
        "theta": -2.8889360899741146
      },
      "geometry": {
        "type": "Polygon",
        "coordinates": [
          [
            [
              1648.928412435505,
              -218.46944030695533
            ],
            [
              756.0,
              -449.0
            ],
            [
              983.0715875644953,
              -1328.5305596930446
            ],
            [
              1876.0,
              -1098.0
            ],
            [
              1648.928412435505,
              -218.46944030695533
            ]
          ]
        ]
      }
    }
  ]
}