{
  "type": "FeatureCollection",
  "features": [
    {
      "type": "Feature",
      "properties": {
        "type": "Datamatrix",
        "rows": 40,
        "cols": 40,
        "polarity": 1
      },
      "geometry": {
        "type": "Polygon",
        "coordinates": [
          [
            [
              576.0,
              -867.0
            ],
            [
              577.0,
              -344.0
            ],
            [
              977.0,
              -336.0
            ],
            [
              974.0,
              -888.0
            ],
            [
              576.0,
              -867.0
            ]
          ]
        ]
      }
    }
  ]
}